pandas_compat/__init__.py
pandas_compat/_version.py
pandas_compat-0.1.1.dist-info/DESCRIPTION.rst
pandas_compat-0.1.1.dist-info/METADATA
pandas_compat-0.1.1.dist-info/RECORD
pandas_compat-0.1.1.dist-info/WHEEL
pandas_compat-0.1.1.dist-info/metadata.json
pandas_compat-0.1.1.dist-info/top_level.txt
